mcp_testing-0.1.0.dist-info/licenses/LICENSE
test_mcp/__init__.py
test_mcp/config.py
test_mcp/agent/__init__.py
test_mcp/agent/agent.py
test_mcp/agent/config.py
test_mcp/agent/main.py
test_mcp/agent/models.py
test_mcp/cli/__init__.py
test_mcp/cli/completion.py
test_mcp/cli/config_commands.py
test_mcp/cli/create_commands.py
test_mcp/cli/main.py
test_mcp/cli/post_command_hooks.py
test_mcp/cli/report_commands.py
test_mcp/cli/reporting_integration.py
test_mcp/cli/setup_commands.py
test_mcp/cli/suggestions.py
test_mcp/cli/test_commands.py
test_mcp/cli/test_execution.py
test_mcp/cli/update_notifier.py
test_mcp/cli/utils.py
test_mcp/config/__init__.py
test_mcp/config/config_manager.py
test_mcp/mcp_client/__init__.py
test_mcp/mcp_client/capability_router.py
test_mcp/mcp_client/client_manager.py
test_mcp/models/__init__.py
test_mcp/models/base.py
test_mcp/models/compliance.py
test_mcp/models/conversational.py
test_mcp/models/factory.py
test_mcp/models/reporting.py
test_mcp/models/security.py
test_mcp/providers/multi_provider_manager.py
test_mcp/providers/openai_provider.py
test_mcp/providers/provider_interface.py
test_mcp/security/__init__.py
test_mcp/security/oauth_tester.py
test_mcp/security/security_tester.py
test_mcp/services/__init__.py
test_mcp/services/reporting_client.py
test_mcp/shared/console_shared.py
test_mcp/shared/file_utils.py
test_mcp/shared/progress_tracker.py
test_mcp/shared/result_models.py
test_mcp/shell_integration/setup_completion.py
test_mcp/templates/__init__.py
test_mcp/templates/claude_system_prompt.txt
test_mcp/testing/__init__.py
test_mcp/testing/compliance/__init__.py
test_mcp/testing/compliance/mcp_compliance_tester.py
test_mcp/testing/conversation/__init__.py
test_mcp/testing/conversation/conversation_judge.py
test_mcp/testing/conversation/conversation_manager.py
test_mcp/testing/conversation/conversation_models.py
test_mcp/testing/conversation/user_simulator.py
test_mcp/testing/core/__init__.py
test_mcp/testing/core/test_models.py
test_mcp/testing/utils/__init__.py
mcp_testing-0.1.0.dist-info/METADATA
mcp_testing-0.1.0.dist-info/WHEEL
mcp_testing-0.1.0.dist-info/entry_points.txt
mcp_testing-0.1.0.dist-info/top_level.txt
mcp_testing-0.1.0.dist-info/RECORD
