Metadata-Version: 2.4
Name: mcp-testing
Version: 0.1.0
Summary: Local testing framework for MCP (Model Context Protocol) servers
Author-email: Antoni Gmitruk <founders@golf.dev>
License: Apache-2.0
Project-URL: Homepage, https://github.com/golf-mcp/golf-testing
Project-URL: Documentation, https://github.com/golf-mcp/golf-testing#readme
Project-URL: Repository, https://github.com/golf-mcp/golf-testing
Project-URL: Bug Tracker, https://github.com/golf-mcp/golf-testing/issues
Keywords: mcp,testing,ai,claude,protocol,cli,local
Classifier: Development Status :: 3 - Alpha
Classifier: Intended Audience :: Developers
Classifier: License :: OSI Approved :: Apache Software License
Classifier: Programming Language :: Python :: 3
Classifier: Programming Language :: Python :: 3.11
Classifier: Programming Language :: Python :: 3.12
Classifier: Programming Language :: Python :: 3.13
Classifier: Topic :: Software Development :: Testing
Classifier: Topic :: Software Development :: Quality Assurance
Classifier: Environment :: Console
Classifier: Operating System :: OS Independent
Requires-Python: >=3.11
License-File: LICENSE
Requires-Dist: pydantic>=2.0.0
Requires-Dist: anthropic>=0.65.0
Requires-Dist: openai>=1.0.0
Requires-Dist: httpx>=0.25.0
Requires-Dist: click>=8.0.0
Requires-Dist: rich>=13.0.0
Requires-Dist: PyYAML>=6.0.0
Requires-Dist: mcp>=1.15.0
Requires-Dist: PyJWT>=2.10.1
Requires-Dist: packaging>=21.0
Provides-Extra: dev
Requires-Dist: pytest>=8.0.0; extra == "dev"
Requires-Dist: pytest-asyncio>=0.21.0; extra == "dev"
Requires-Dist: pytest-httpx>=0.21.0; extra == "dev"
Requires-Dist: black>=24.0.0; extra == "dev"
Requires-Dist: ruff>=0.13.0; extra == "dev"
Requires-Dist: mypy>=1.18.0; extra == "dev"
Requires-Dist: pre-commit>=4.0.0; extra == "dev"
Provides-Extra: ci
Requires-Dist: pytest>=8.0.0; extra == "ci"
Requires-Dist: pytest-asyncio>=0.21.0; extra == "ci"
Requires-Dist: pytest-cov>=4.0.0; extra == "ci"
Requires-Dist: pytest-xdist>=3.0.0; extra == "ci"
Dynamic: license-file
